mango.py
python_mango-0.1.7.dist-info/DESCRIPTION.rst
python_mango-0.1.7.dist-info/METADATA
python_mango-0.1.7.dist-info/RECORD
python_mango-0.1.7.dist-info/WHEEL
python_mango-0.1.7.dist-info/metadata.json
python_mango-0.1.7.dist-info/top_level.txt
