Metadata-Version: 2.0
Name: python-mango
Version: 0.1.7
Summary: Mango: simple MongoDb wrapper
Home-page: https://laminko.github.io/mango/
Author: laminko
Author-email: lminko.lmk@gmail.com
License: MIT
Platform: Any
Classifier: Development Status :: 3 - Alpha
Classifier: Environment :: Console
Classifier: Intended Audience :: Developers
Classifier: Intended Audience :: System Administrators
Classifier: License :: OSI Approved :: MIT License
Classifier: Operating System :: MacOS :: MacOS X
Classifier: Operating System :: Microsoft :: Windows
Classifier: Operating System :: POSIX
Classifier: Programming Language :: Python
Classifier: Topic :: Utilities
Classifier: Topic :: Software Development :: Libraries
Requires-Dist: pymongo
